{"id":"layouts/Admin/Tools/actions.js","dependencies":[{"name":"/var/www/html/utter/package.json","includedInParent":true,"mtime":1537713411456},{"name":"/var/www/html/utter/.babelrc","includedInParent":true,"mtime":1537642482682},{"name":"react-hot-loader","parent":"/var/www/html/utter/client/src/layouts/Admin/Tools/actions.js","resolved":"/var/www/html/utter/node_modules/react-hot-loader/index.js"},{"name":"../../../utils/reduxUtils.js","loc":{"line":1,"column":27},"parent":"/var/www/html/utter/client/src/layouts/Admin/Tools/actions.js","resolved":"/var/www/html/utter/client/src/utils/reduxUtils.js"},{"name":"./types","loc":{"line":3,"column":31},"parent":"/var/www/html/utter/client/src/layouts/Admin/Tools/actions.js","resolved":"/var/www/html/utter/client/src/layouts/Admin/Tools/types.js"}],"generated":{"js":"'use strict';\n\nObject.defineProperty(exports, \"__esModule\", {\n  value: true\n});\n\nvar _reduxUtils = require('../../../utils/reduxUtils.js');\n\nvar _types = require('./types');\n\n(function () {\n  var enterModule = require('react-hot-loader').enterModule;\n\n  enterModule && enterModule(module);\n})();\n\nvar _default = {\n  request: function request() {\n    var state = arguments.length > 0 && arguments[0] !== undefined ? arguments[0] : {};\n    return (0, _reduxUtils.createAction)(_types.LOAD_USERS_ASYNC.REQUEST, state);\n  }\n};\nexports.default = _default;\n;\n\n(function () {\n  var reactHotLoader = require('react-hot-loader').default;\n\n  var leaveModule = require('react-hot-loader').leaveModule;\n\n  if (!reactHotLoader) {\n    return;\n  }\n\n  reactHotLoader.register(_default, 'default', '/var/www/html/utter/client/src/layouts/Admin/Tools/actions.js');\n  leaveModule(module);\n})();\n\n;","map":{"mappings":[{"generated":{"line":7,"column":0},"source":"layouts/Admin/Tools/actions.js","original":{"line":1,"column":0}},{"generated":{"line":9,"column":0},"source":"layouts/Admin/Tools/actions.js","original":{"line":3,"column":0}},{"generated":{"line":17,"column":15},"source":"layouts/Admin/Tools/actions.js","original":{"line":5,"column":15}},{"name":"request","generated":{"line":18,"column":0},"source":"layouts/Admin/Tools/actions.js","original":{"line":6,"column":2}},{"generated":{"line":18,"column":11},"source":"layouts/Admin/Tools/actions.js","original":{"line":6,"column":11}},{"generated":{"line":19,"column":0},"source":"layouts/Admin/Tools/actions.js","original":{"line":6,"column":11}},{"name":"state","generated":{"line":19,"column":8},"source":"layouts/Admin/Tools/actions.js","original":{"line":6,"column":12}},{"generated":{"line":19,"column":13},"source":"layouts/Admin/Tools/actions.js","original":{"line":6,"column":11}},{"generated":{"line":19,"column":84},"source":"layouts/Admin/Tools/actions.js","original":{"line":6,"column":20}},{"generated":{"line":19,"column":86},"source":"layouts/Admin/Tools/actions.js","original":{"line":6,"column":11}},{"generated":{"line":20,"column":0},"source":"layouts/Admin/Tools/actions.js","original":{"line":6,"column":11}},{"generated":{"line":20,"column":11},"source":"layouts/Admin/Tools/actions.js","original":{"line":6,"column":27}},{"name":"LOAD_USERS_ASYNC","generated":{"line":20,"column":41},"source":"layouts/Admin/Tools/actions.js","original":{"line":6,"column":40}},{"name":"REQUEST","generated":{"line":20,"column":65},"source":"layouts/Admin/Tools/actions.js","original":{"line":6,"column":57}},{"generated":{"line":20,"column":72},"source":"layouts/Admin/Tools/actions.js","original":{"line":6,"column":27}},{"name":"state","generated":{"line":20,"column":74},"source":"layouts/Admin/Tools/actions.js","original":{"line":6,"column":66}},{"generated":{"line":20,"column":79},"source":"layouts/Admin/Tools/actions.js","original":{"line":6,"column":27}},{"generated":{"line":20,"column":80},"source":"layouts/Admin/Tools/actions.js","original":{"line":6,"column":11}},{"generated":{"line":21,"column":0},"source":"layouts/Admin/Tools/actions.js","original":{"line":6,"column":11}},{"generated":{"line":22,"column":0},"source":"layouts/Admin/Tools/actions.js","original":{"line":5,"column":15}}],"sources":{"layouts/Admin/Tools/actions.js":"import {createAction} from '../../../utils/reduxUtils.js'\n\nimport {LOAD_USERS_ASYNC} from './types'\n\nexport default {\n  request: (state = {}) => createAction(LOAD_USERS_ASYNC.REQUEST, state)\n}\n"},"lineCount":null}},"hash":"9d7900d5d3cc7e4daa2bbc4a508feecb","cacheData":{"env":{}}}