{"id":"containers/Pagination/actions.js","dependencies":[{"name":"/var/www/html/utter/package.json","includedInParent":true,"mtime":1537713411456},{"name":"/var/www/html/utter/.babelrc","includedInParent":true,"mtime":1537642482682},{"name":"react-hot-loader","parent":"/var/www/html/utter/client/src/containers/Pagination/actions.js","resolved":"/var/www/html/utter/node_modules/react-hot-loader/index.js"},{"name":"lodash/capitalize","loc":{"line":1,"column":23},"parent":"/var/www/html/utter/client/src/containers/Pagination/actions.js","resolved":"/var/www/html/utter/node_modules/lodash/capitalize.js"},{"name":"./types.js","loc":{"line":2,"column":29},"parent":"/var/www/html/utter/client/src/containers/Pagination/actions.js","resolved":"/var/www/html/utter/client/src/containers/Pagination/types.js"},{"name":"../../utils/reduxUtils.js","loc":{"line":3,"column":27},"parent":"/var/www/html/utter/client/src/containers/Pagination/actions.js","resolved":"/var/www/html/utter/client/src/utils/reduxUtils.js"},{"name":"./selectors.js","loc":{"line":4,"column":31},"parent":"/var/www/html/utter/client/src/containers/Pagination/actions.js","resolved":"/var/www/html/utter/client/src/containers/Pagination/selectors.js"}],"generated":{"js":"'use strict';\n\nObject.defineProperty(exports, \"__esModule\", {\n  value: true\n});\nexports.paginateRequest = paginateRequest;\n\nvar _capitalize = require('lodash/capitalize');\n\nvar _capitalize2 = _interopRequireDefault(_capitalize);\n\nvar _types = require('./types.js');\n\nvar _reduxUtils = require('../../utils/reduxUtils.js');\n\nvar _selectors = require('./selectors.js');\n\nfunction _interopRequireDefault(obj) { return obj && obj.__esModule ? obj : { default: obj }; }\n\n(function () {\n  var enterModule = require('react-hot-loader').enterModule;\n\n  enterModule && enterModule(module);\n})();\n\nfunction paginateRequest(resource, state) {\n  resource = (0, _capitalize2.default)(resource);\n  return function (dispatch, getState) {\n    var state = getState();\n    var page = (0, _selectors.selectCourseProp)(state);\n\n    // dispatch(editExistingItem('Level', currentLevel))\n    dispatch({ type: _types.PAGINATE_ASYNC.REQUEST });\n  };\n}\n\n// export default {\n//   request: param => createAction(PAGINATE_ASYNC.REQUEST, param),\n//   success: param => createAction(PAGINATE_ASYNC.SUCCESS, param),\n//   error: error => createAction(PAGINATE_ASYNC.ERROR, error),\n//   reset: () => createAction(PAGINATE_ASYNC.RESET)\n// }\n\n;\n\n(function () {\n  var reactHotLoader = require('react-hot-loader').default;\n\n  var leaveModule = require('react-hot-loader').leaveModule;\n\n  if (!reactHotLoader) {\n    return;\n  }\n\n  reactHotLoader.register(paginateRequest, 'paginateRequest', '/var/www/html/utter/client/src/containers/Pagination/actions.js');\n  leaveModule(module);\n})();\n\n;","map":{"mappings":[{"name":"paginateRequest","generated":{"line":6,"column":8},"source":"containers/Pagination/actions.js","original":{"line":6,"column":16}},{"name":"paginateRequest","generated":{"line":6,"column":26},"source":"containers/Pagination/actions.js","original":{"line":6,"column":16}},{"generated":{"line":8,"column":0},"source":"containers/Pagination/actions.js","original":{"line":1,"column":0}},{"generated":{"line":12,"column":0},"source":"containers/Pagination/actions.js","original":{"line":2,"column":0}},{"generated":{"line":14,"column":0},"source":"containers/Pagination/actions.js","original":{"line":3,"column":0}},{"generated":{"line":16,"column":0},"source":"containers/Pagination/actions.js","original":{"line":4,"column":0}},{"generated":{"line":26,"column":0},"source":"containers/Pagination/actions.js","original":{"line":6,"column":7}},{"name":"paginateRequest","generated":{"line":26,"column":9},"source":"containers/Pagination/actions.js","original":{"line":6,"column":16}},{"generated":{"line":26,"column":24},"source":"containers/Pagination/actions.js","original":{"line":6,"column":7}},{"name":"resource","generated":{"line":26,"column":25},"source":"containers/Pagination/actions.js","original":{"line":6,"column":32}},{"generated":{"line":26,"column":33},"source":"containers/Pagination/actions.js","original":{"line":6,"column":7}},{"name":"state","generated":{"line":26,"column":35},"source":"containers/Pagination/actions.js","original":{"line":6,"column":42}},{"generated":{"line":26,"column":40},"source":"containers/Pagination/actions.js","original":{"line":6,"column":7}},{"generated":{"line":26,"column":42},"source":"containers/Pagination/actions.js","original":{"line":6,"column":49}},{"name":"resource","generated":{"line":27,"column":0},"source":"containers/Pagination/actions.js","original":{"line":7,"column":2}},{"generated":{"line":27,"column":13},"source":"containers/Pagination/actions.js","original":{"line":7,"column":13}},{"name":"resource","generated":{"line":27,"column":39},"source":"containers/Pagination/actions.js","original":{"line":7,"column":24}},{"generated":{"line":27,"column":47},"source":"containers/Pagination/actions.js","original":{"line":7,"column":13}},{"generated":{"line":27,"column":48},"source":"containers/Pagination/actions.js","original":{"line":7,"column":2}},{"generated":{"line":28,"column":0},"source":"containers/Pagination/actions.js","original":{"line":8,"column":2}},{"generated":{"line":28,"column":9},"source":"containers/Pagination/actions.js","original":{"line":8,"column":9}},{"name":"dispatch","generated":{"line":28,"column":19},"source":"containers/Pagination/actions.js","original":{"line":8,"column":10}},{"generated":{"line":28,"column":27},"source":"containers/Pagination/actions.js","original":{"line":8,"column":9}},{"name":"getState","generated":{"line":28,"column":29},"source":"containers/Pagination/actions.js","original":{"line":8,"column":20}},{"generated":{"line":28,"column":37},"source":"containers/Pagination/actions.js","original":{"line":8,"column":9}},{"generated":{"line":28,"column":39},"source":"containers/Pagination/actions.js","original":{"line":8,"column":33}},{"generated":{"line":29,"column":0},"source":"containers/Pagination/actions.js","original":{"line":9,"column":4}},{"name":"state","generated":{"line":29,"column":8},"source":"containers/Pagination/actions.js","original":{"line":9,"column":10}},{"name":"getState","generated":{"line":29,"column":16},"source":"containers/Pagination/actions.js","original":{"line":9,"column":18}},{"generated":{"line":29,"column":26},"source":"containers/Pagination/actions.js","original":{"line":9,"column":4}},{"generated":{"line":30,"column":0},"source":"containers/Pagination/actions.js","original":{"line":10,"column":4}},{"name":"page","generated":{"line":30,"column":8},"source":"containers/Pagination/actions.js","original":{"line":10,"column":10}},{"generated":{"line":30,"column":15},"source":"containers/Pagination/actions.js","original":{"line":10,"column":17}},{"name":"state","generated":{"line":30,"column":48},"source":"containers/Pagination/actions.js","original":{"line":10,"column":34}},{"generated":{"line":30,"column":53},"source":"containers/Pagination/actions.js","original":{"line":10,"column":17}},{"generated":{"line":30,"column":54},"source":"containers/Pagination/actions.js","original":{"line":10,"column":4}},{"generated":{"line":32,"column":0},"source":"containers/Pagination/actions.js","original":{"line":12,"column":4}},{"name":"dispatch","generated":{"line":33,"column":0},"source":"containers/Pagination/actions.js","original":{"line":13,"column":4}},{"generated":{"line":33,"column":13},"source":"containers/Pagination/actions.js","original":{"line":13,"column":13}},{"name":"type","generated":{"line":33,"column":15},"source":"containers/Pagination/actions.js","original":{"line":13,"column":14}},{"name":"PAGINATE_ASYNC","generated":{"line":33,"column":21},"source":"containers/Pagination/actions.js","original":{"line":13,"column":20}},{"name":"REQUEST","generated":{"line":33,"column":43},"source":"containers/Pagination/actions.js","original":{"line":13,"column":35}},{"generated":{"line":33,"column":50},"source":"containers/Pagination/actions.js","original":{"line":13,"column":13}},{"generated":{"line":33,"column":52},"source":"containers/Pagination/actions.js","original":{"line":13,"column":4}},{"generated":{"line":34,"column":0},"source":"containers/Pagination/actions.js","original":{"line":14,"column":3}},{"generated":{"line":34,"column":3},"source":"containers/Pagination/actions.js","original":{"line":8,"column":2}},{"generated":{"line":35,"column":0},"source":"containers/Pagination/actions.js","original":{"line":15,"column":1}},{"generated":{"line":37,"column":0},"source":"containers/Pagination/actions.js","original":{"line":17,"column":0}},{"generated":{"line":38,"column":0},"source":"containers/Pagination/actions.js","original":{"line":18,"column":0}},{"generated":{"line":39,"column":0},"source":"containers/Pagination/actions.js","original":{"line":19,"column":0}},{"generated":{"line":40,"column":0},"source":"containers/Pagination/actions.js","original":{"line":20,"column":0}},{"generated":{"line":41,"column":0},"source":"containers/Pagination/actions.js","original":{"line":21,"column":0}},{"generated":{"line":42,"column":0},"source":"containers/Pagination/actions.js","original":{"line":22,"column":0}},{"name":"paginateRequest","generated":{"line":55,"column":26},"source":"containers/Pagination/actions.js","original":{"line":6,"column":16}}],"sources":{"containers/Pagination/actions.js":"import capitalize from 'lodash/capitalize'\nimport {PAGINATE_ASYNC} from './types.js'\nimport {createAction} from '../../utils/reduxUtils.js'\nimport {selectCourseProp} from './selectors.js'\n\nexport function paginateRequest(resource, state) {\n  resource = capitalize(resource)\n  return (dispatch, getState) => {\n    const state = getState()\n    const page = selectCourseProp(state)\n\n    // dispatch(editExistingItem('Level', currentLevel))\n    dispatch({type: PAGINATE_ASYNC.REQUEST})\n  }\n}\n\n// export default {\n//   request: param => createAction(PAGINATE_ASYNC.REQUEST, param),\n//   success: param => createAction(PAGINATE_ASYNC.SUCCESS, param),\n//   error: error => createAction(PAGINATE_ASYNC.ERROR, error),\n//   reset: () => createAction(PAGINATE_ASYNC.RESET)\n// }\n"},"lineCount":null}},"hash":"58eb5746a9fd6acc0ad9fc6efb42630d","cacheData":{"env":{}}}